MANIFEST.in
setup.py
MirrorMirror2.egg-info/PKG-INFO
MirrorMirror2.egg-info/SOURCES.txt
MirrorMirror2.egg-info/dependency_links.txt
MirrorMirror2.egg-info/entry_points.txt
MirrorMirror2.egg-info/requires.txt
MirrorMirror2.egg-info/top_level.txt
mirror_mirror/__init__.py
mirror_mirror/calendardisplay.py
mirror_mirror/clock.py
mirror_mirror/events.py
mirror_mirror/main.py
mirror_mirror/motd.py
mirror_mirror/news.py
mirror_mirror/server.py
mirror_mirror/weather.py
mirror_mirror/resources/css/animated_weather_icons.css
mirror_mirror/resources/css/main.css
mirror_mirror/resources/css/normalize.css
mirror_mirror/resources/css/weather.css
mirror_mirror/resources/events/client.json
mirror_mirror/resources/js/main.js
mirror_mirror/resources/js/vendor/jquery-1.11.3.min.js
mirror_mirror/resources/js/vendor/jquery.simpleWeather.min.js
mirror_mirror/resources/js/vendor/modernizr-2.8.3.min.js
mirror_mirror/resources/js/vendor/moment.js
mirror_mirror/sensors/__init__.py
mirror_mirror/sensors/emulate.py