Metadata-Version: 1.0
Name: MirrorMirror2
Version: 1.1.5
Summary: A mirror mirror GUI
Home-page: http://github.com/nak/mirror_mirror
Author: John Rusnak
Author-email: john.j.rusnak@att.net
License: LGPL
Keywords: mirror mirror_mirror
Platform: UNKNOWN
